rotten_korean_romanizer/__init__.py
rotten_korean_romanizer/romanizer.py
rotten_korean_romanizer-0.1.0.dist-info/LICENSE
rotten_korean_romanizer-0.1.0.dist-info/METADATA
rotten_korean_romanizer-0.1.0.dist-info/WHEEL
rotten_korean_romanizer-0.1.0.dist-info/top_level.txt
rotten_korean_romanizer-0.1.0.dist-info/RECORD
