Metadata-Version: 2.1
Name: rotten_korean_romanizer
Version: 0.1.0
Summary: A Python library for romanizing Korean text
Home-page: https://github.com/developer0hye/rotten-korean-romanizer
Author: Yonghye Kwon
Author-email: developer.0hye@gmail.com
Classifier: Programming Language :: Python :: 3
Classifier: License :: OSI Approved :: MIT License
Classifier: Operating System :: OS Independent
Requires-Python: >=3.6
License-File: LICENSE
